openfunnel_telemetry/openfunneltelemetrybase/__init__.py
openfunnel_telemetry/openfunneltelemetrybase/openfunneltelemetrybase.py
openfunnel_telemetry/openfunneltelemetrydecorator/openfunnel_telemetry_decorator.py
openfunnel_telemetry/openfunneltelemetrypostinstall/openfunnel_telemetry_post_install.py
openfunnel_telemetry-1.0.0.dist-info/METADATA
openfunnel_telemetry-1.0.0.dist-info/WHEEL
openfunnel_telemetry-1.0.0.dist-info/RECORD
