Metadata-Version: 2.1
Name: openfunnel-telemetry
Version: 1.0.0
Summary: OpenFunnel Telemetry Python SDK for Code Level Telemetry
License: MIT
Author: Fenil Suchak
Author-email: fenil.suchak1@gmail.com
Requires-Python: >=3.11,<4.0
Classifier: License :: OSI Approved :: MIT License
Classifier: Programming Language :: Python :: 3
Classifier: Programming Language :: Python :: 3.11
Classifier: Programming Language :: Python :: 3.12
